google_trends_mcp/__init__.py
google_trends_mcp/server.py
google_trends_mcp_qihoo-1.0.3.dist-info/METADATA
google_trends_mcp_qihoo-1.0.3.dist-info/WHEEL
google_trends_mcp_qihoo-1.0.3.dist-info/entry_points.txt
google_trends_mcp_qihoo-1.0.3.dist-info/licenses/LICENSE
google_trends_mcp_qihoo-1.0.3.dist-info/RECORD
