Metadata-Version: 2.4
Name: google-trends-mcp-qihoo
Version: 1.0.3
Summary: Google Trends MCP Server for analyzing search trends
Project-URL: Homepage, https://github.com/donghai88/google-trends-mcp-server
Project-URL: Repository, https://github.com/donghai88/google-trends-mcp-server
Project-URL: Issues, https://github.com/donghai88/google-trends-mcp-server/issues
Author-email: 董海 <123131683@qq.com>
License-Expression: MIT
License-File: LICENSE
Keywords: ai,google-trends,llm,mcp,model-context-protocol,search-trends
Classifier: Development Status :: 4 - Beta
Classifier: Intended Audience :: Developers
Classifier: License :: OSI Approved :: MIT License
Classifier: Programming Language :: Python :: 3
Classifier: Programming Language :: Python :: 3.8
Classifier: Programming Language :: Python :: 3.9
Classifier: Programming Language :: Python :: 3.10
Classifier: Programming Language :: Python :: 3.11
Classifier: Programming Language :: Python :: 3.12
Classifier: Topic :: Software Development :: Libraries :: Python Modules
Requires-Python: >=3.8
Requires-Dist: mcp>=1.0.0
Requires-Dist: pytrends>=4.9.0
